{"_id":"28e378a0-a547-11ec-8197-cb4fea2278c1","_parent":"https://kabardinovd.com/posts/cdn/","replying_to":"","replying_to_uid":"","message":"Sexy Einheimische  Ich sah auf und begegnete ihrem Blick Die Haine fliegen vorbei - der Zug rast nach Osten Der Zirkus brГјllte wild und begeistert Diana bog sich leicht und erlaubte allen MГ¤nnern im Raum, ihren sexy und einladenden KГ¶rper zu bewundern  <a href=\"https://nacktbildceleb.com/celebirties-nackt/nackt-in-einer-limousine-7865.php\" title=\"Nackt In Einer Limousine boneme porn \">Nackt In Einer Limousine boneme porn </a> Ich hГ¶rte auf darГјber nachzudenken, was ich als nГ¤chstes tun sollte Selbst im Traum lassen sie sich nicht gehen \", lachte sie,вЂћ saugte leicht und natГјrlich Max, Denis, ich Vielleicht trГ¤ume ich, dass du trГ¤umst .","name":"Nacktbildceleb_gug","email":"db9424163bd40de5095e423f18674e12","hp":"","date":1647448559}