{"_id":"6592b150-7445-11eb-9a06-871248fa05f9","_parent":"https://kabardinovd.com/posts/10-things-I-learned-building-my-personal-blog/","replying_to":"","replying_to_uid":"","message":"ЧИСТЫЕ КОМНАТЫ \r\nОдним из основных направлений в деятельности компании «Термопроцесс» является разработка и производство комнат избыточного давления или чистых комнат.  Чистая комната предназначена для проведения различных видов лакокрасочных работ, позволяя получать при этом поверхности стабильно высокого качества за счёт создания оптимального микроклимата в рабочей зоне, очищенной от примесей, мелкодисперсионных взвесей, аэрозолей.  \r\n<a href=http://www.termoprocess.ru/katalog/konvektivnye_sushilnye_kamery_dlya_drevesiniy/konvektivnye_sushilnye_kamery_s_frontalnoj_zagruzkoj/>http://www.termoprocess.ru/katalog/konvektivnye_sushilnye_kamery_dlya_drevesiniy/konvektivnye_sushilnye_kamery_s_frontalnoj_zagruzkoj/</a> ШЛИФОВАЛЬНЫЕ СТОЛЫ \r\nШлифовальный стол СШП предназначен для удаления пыли, получаемой в процессе ручного шлифования древесины. \r\n \r\nШлифовальные столы поставляются с рабочей длиной 2.2м и 3,3м. и шириной 1,1м","name":"AaronmaB","email":"f48a16388f32804903332fdcf064604e","hp":"","date":1613912697}